{
  "blogs": [
    {
      "title": "Adventures in Geography: Exploring World Wonders",
      "author": "Explorer Nate",
      "id": 1,
      "content": "Embark on an exciting geographical journey with Explorer Nate to uncover the mysteries of world wonders. This educational blog caters to children aged 7 to 9, introducing them to the fascinating world of geography through captivating stories, interactive maps, and virtual tours. Explore the towering peaks of the Himalayas, dive into the depths of the Great Barrier Reef, and unravel the secrets of cultural diversity across the continents. From understanding different landforms, such as mountains and rivers, to appreciating the rich tapestry of global cultures, and honing essential map reading skills, this blog provides a rich learning experience that sparks curiosity about the world and fosters a sense of global awareness.",
      "topic": "Geography",
      "age_range": "7-9",
      "learning_objectives": [
        "Landforms",
        "Cultural Diversity",
        "Map Reading Skills"
      ],
      "interactive_activities": [
        "Virtual World Tours",
        "Geography Games"
      ],
      "recommended_resources": [
        "Children's Atlas",
        "Educational Geography Apps"
      ],
      "assessment_methods": [
        "Map Quiz",
        "Geography Challenge"
      ],
      "engagement_level": "High",
      "image": "https://example.com/geography_adventures.jpg"
    },
    {
      "title": "Math Marvels: Fun with Fractions",
      "author": "Math Magician Emma",
      "id": 2,
      "content": "Join Math Magician Emma on an enchanting journey into the world of fractions. This blog, tailored for children aged 7 to 9, transforms the seemingly complex world of fractions into a captivating adventure. Dive into the magical realm of mathematics where understanding fractions, their operations, and real-life applications becomes an enjoyable experience. Through hands-on activities like the Fraction Pizza Party, where children get to create delicious slices while learning about fractions, and engaging games like Fraction Bingo, Math Marvels sparks a love for numbers and problem-solving. With the Fraction Magic Show, witness the magic of math unravel, making fractions not only understandable but also fascinating for young minds.",
      "topic": "Mathematics",
      "age_range": "7-9",
      "learning_objectives": [
        "Understanding Fractions",
        "Fraction Operations",
        "Real-life Applications"
      ],
      "interactive_activities": [
        "Fraction Pizza Party",
        "Fraction Bingo"
      ],
      "recommended_resources": [
        "Children's Math Books",
        "Fraction Manipulatives"
      ],
      "assessment_methods": [
        "Fraction Magic Show",
        "Fraction Problem Solving"
      ],
      "engagement_level": "High",
      "image": "https://example.com/math_marvels.jpg"
    },
    {
      "title": "Language Explorers: Adventures in Word Building",
      "author": "Word Wizard Ava",
      "id": 3,
      "content": "Embark on word-building adventures with Word Wizard Ava. This blog for children aged 7 to 9 focuses on enhancing language skills through spelling games, vocabulary challenges, and creative word exploration. Dive into the magic of language as Word Wizard Ava takes young readers on a journey of words, from spelling bees that buzz with excitement to word-building games that unleash creativity. Recommended resources include captivating children's spelling books and engaging language learning apps, making the learning process both educational and entertaining. Assessment methods, such as the Spelling Challenge and Word Building Project, ensure a thorough understanding of language concepts, while the high engagement level keeps young minds eager to explore the world of words.",
      "topic": "Language Arts",
      "age_range": "7-9",
      "learning_objectives": [
        "Spelling Skills",
        "Vocabulary Expansion",
        "Word Recognition"
      ],
      "interactive_activities": [
        "Spelling Bee Contest",
        "Word Building Games"
      ],
      "recommended_resources": [
        "Children's Spelling Books",
        "Language Learning Apps"
      ],
      "assessment_methods": [
        "Spelling Challenge",
        "Word Building Project"
      ],
      "engagement_level": "High",
      "image": "https://example.com/language_explorers.jpg"
    },
    {
      "title": "Science Explorers: Amazing Plant Kingdom",
      "author": "Botany Explorer Liam",
      "id": 4,
      "content": "Join Botany Explorer Liam on a botanical adventure to explore the amazing world of plants. This educational blog for children aged 7 to 9 introduces botany concepts through hands-on experiments, plant observations, and gardening activities. Immerse yourself in the wonders of the plant kingdom as Botany Explorer Liam guides young minds through the plant life cycle, the various parts of a plant, and the fascinating process of photosynthesis. Engage in DIY plant experiments and embark on the journey of growing your own garden, fostering a deep connection with nature. Recommended resources include children's botany books and botany kits for kids, ensuring a holistic understanding of plant biology. Assessment methods, such as the Botanical Quiz and Plant Observation Journal, make the learning process both informative and enjoyable, with a high engagement level capturing the curiosity of young scientists.",
      "topic": "Botany",
      "age_range": "7-9",
      "learning_objectives": [
        "Plant Life Cycle",
        "Parts of a Plant",
        "Photosynthesis"
      ],
      "interactive_activities": [
        "DIY Plant Experiments",
        "Grow Your Own Garden"
      ],
      "recommended_resources": [
        "Children's Botany Books",
        "Botany Kits for Kids"
      ],
      "assessment_methods": [
        "Botanical Quiz",
        "Plant Observation Journal"
      ],
      "engagement_level": "High",
      "image": "https://example.com/botany_explorers.jpg"
    },
    {
      "title": "History Explorers: Time Travel to Ancient Civilizations",
      "author": "Time Voyager Sofia",
      "id": 5,
      "content": "Time Voyager Sofia invites young historians to time travel to ancient civilizations. This educational blog for children aged 7 to 9 combines historical facts with interactive stories, bringing the past to life in an engaging and educational way. Step into the shoes of a time traveler as Time Voyager Sofia guides young historians through the wonders of ancient civilizations. This blog, designed for children aged 7 to 9, seamlessly blends historical facts with interactive stories, offering a unique learning experience. Engage in activities like the Time Traveler's Journal and embark on a DIY archaeological dig to uncover the mysteries of history. Recommended resources include captivating children's history books and historical maps, providing a rich tapestry of knowledge. Assessment methods, such as the Historical Time Capsule Project and Time Traveler's Quiz, ensure a comprehensive understanding of historical narratives with a moderate engagement level that balances education and entertainment.",
      "topic": "History",
      "age_range": "7-9",
      "learning_objectives": [
        "Ancient Civilizations",
        "Cultural Heritage",
        "Historical Narratives"
      ],
      "interactive_activities": [
        "Time Traveler's Journal",
        "DIY Archaeological Dig"
      ],
      "recommended_resources": [
        "Children's History Books",
        "Historical Maps"
      ],
      "assessment_methods": [
        "Historical Time Capsule Project",
        "Time Traveler's Quiz"
      ],
      "engagement_level": "Moderate",
      "image": "https://example.com/history_explorers.jpg"
    },
    {
      "title": "Space Explorers: Journey to the Stars",
      "author": "Astronaut Alex",
      "id": 6,
      "content": "Astronaut Alex takes young space enthusiasts on an extraordinary journey to the stars. This blog for children aged 7 to 9 explores the wonders of the universe through exciting space facts, interactive simulations, and cosmic adventures. Join Astronaut Alex on a cosmic odyssey as young space enthusiasts embark on an educational journey to explore the mysteries of the universe. Designed for children aged 7 to 9, this blog delves into topics such as the solar system, galaxies, and space exploration. Engage in virtual space tours, gaze at the starry night sky, and absorb fascinating space facts that ignite curiosity. Recommended resources include captivating children's astronomy books and telescopes for beginners, providing a gateway to the vastness of space. Assessment methods, such as the Galactic Explorer Quiz and Space Adventure Project, ensure a stellar comprehension of astronomical concepts with a high engagement level that sparks a love for celestial exploration.",
      "topic": "Astronomy",
      "age_range": "7-9",
      "learning_objectives": [
        "Solar System",
        "Galaxies",
        "Space Exploration"
      ],
      "interactive_activities": [
        "Virtual Space Tours",
        "Starry Night Sky Observation"
      ],
      "recommended_resources": [
        "Children's Astronomy Books",
        "Telescope for Beginners"
      ],
      "assessment_methods": [
        "Galactic Explorer Quiz",
        "Space Adventure Project"
      ],
      "engagement_level": "High",
      "image": "https://example.com/space_explorers.jpg"
    },
    {
      "title": "Art Explorers: Creative Masterpieces Unleashed",
      "author": "Art Maestro Zoe",
      "id": 7,
      "content": "Join Art Maestro Zoe on a creative journey where young artists unleash their imaginations. This educational blog for children aged 7 to 9 explores various art forms, techniques, and encourages self-expression through hands-on artistic endeavors. Dive into the vibrant world of art with Art Maestro Zoe, guiding young artists aged 7 to 9 on a journey of creative exploration. This blog explores art techniques, creative expression, and art history, fostering a love for self-expression through hands-on artistic endeavors. Engage in DIY art projects, explore an art appreciation gallery, and discover the world of colors, shapes, and forms. Recommended resources include inspiring children's art books and an art supplies set, ensuring a rich palette of artistic knowledge. Assessment methods, such as the Art Showcase and Creative Expression Portfolio, encourage young artists to showcase their unique talents with a high engagement level that celebrates the diversity of artistic expression.",
      "topic": "Art",
      "age_range": "7-9",
      "learning_objectives": [
        "Art Techniques",
        "Creative Expression",
        "Art History"
      ],
      "interactive_activities": [
        "DIY Art Projects",
        "Art Appreciation Gallery"
      ],
      "recommended_resources": [
        "Children's Art Books",
        "Art Supplies Set"
      ],
      "assessment_methods": [
        "Art Showcase",
        "Creative Expression Portfolio"
      ],
      "engagement_level": "High",
      "image": "https://example.com/art_explorers.jpg"
    },
    {
      "title": "Ecology Explorers: Protecting Our Planet",
      "author": "Eco Warrior Ethan",
      "id": 8,
      "content": "Eco Warrior Ethan leads young environmentalists on a mission to protect our planet. This blog for children aged 7 to 9 delves into ecological concepts, sustainability practices, and inspires eco-friendly actions for a greener future. Follow Eco Warrior Ethan on a mission to protect our planet as young environmentalists aged 7 to 9 explore ecological concepts, sustainability practices, and eco-friendly actions. Engage in eco-friendly projects, take on nature conservation challenges, and discover the importance of environmental responsibility. Recommended resources include insightful children's ecology books and an environmental science kit, providing a foundation for understanding and preserving the delicate balance of our planet. Assessment methods, such as the Eco Warrior Challenge and Eco-friendly Project Showcase, empower young minds to make a positive impact on the environment with a high engagement level that instills a sense of environmental stewardship.",
      "topic": "Ecology",
      "age_range": "7-9",
      "learning_objectives": [
        "Ecosystems",
        "Conservation",
        "Environmental Responsibility"
      ],
      "interactive_activities": [
        "Eco-friendly Projects",
        "Nature Conservation Challenges"
      ],
      "recommended_resources": [
        "Children's Ecology Books",
        "Environmental Science Kit"
      ],
      "assessment_methods": [
        "Eco Warrior Challenge",
        "Eco-friendly Project Showcase"
      ],
      "engagement_level": "High",
      "image": "https://example.com/ecology_explorers.jpg"
    },
    {
      "title": "Coding Adventures: Exploring the Digital World",
      "author": "Code Explorer Oliver",
      "id": 9,
      "content": "Code Explorer Oliver invites young tech enthusiasts on a coding adventure into the digital world. This educational blog for children aged 7 to 9 introduces basic coding concepts, computational thinking, and hands-on coding activities. Embark on a coding adventure with Code Explorer Oliver, inspiring young tech enthusiasts aged 7 to 9 to explore the digital world. This blog introduces basic coding concepts, computational thinking, and hands-on coding activities that lay the foundation for future technological literacy. Engage in coding challenges, tackle DIY coding projects, and discover the power of problem-solving through coding. Recommended resources include engaging children's coding books and coding kits for beginners, providing a gateway to the exciting world of programming. Assessment methods, such as the Code Explorer Challenge and Coding Project Showcase, encourage young minds to unlock the potential of technology with a high engagement level that sparks a passion for coding.",
      "topic": "Computer Science",
      "age_range": "7-9",
      "learning_objectives": [
        "Basic Coding Concepts",
        "Algorithmic Thinking",
        "Problem Solving"
      ],
      "interactive_activities": [
        "Coding Challenges",
        "DIY Coding Projects"
      ],
      "recommended_resources": [
        "Children's Coding Books",
        "Coding Kits for Beginners"
      ],
      "assessment_methods": [
        "Code Explorer Challenge",
        "Coding Project Showcase"
      ],
      "engagement_level": "High",
      "image": "https://example.com/coding_adventures.jpg"
    },
    {
      "title": "Music Explorers: Harmonies Across Cultures",
      "author": "Melody Explorer Mia",
      "id": 10,
      "content": "Melody Explorer Mia takes young music enthusiasts on a cultural journey exploring harmonies from around the world. This educational blog for children aged 7 to 9 introduces musical concepts, instruments, and encourages a love for diverse melodies. Join Melody Explorer Mia on a cultural journey, where young music enthusiasts aged 7 to 9 explore harmonies from around the world. This blog introduces musical concepts, instruments, and encourages a love for diverse melodies. Engage in DIY musical instruments, showcase global music, and discover the universal language of music. Recommended resources include captivating children's music books and musical instrument kits, providing a symphony of knowledge. Assessment methods, such as the Melody Explorer Quiz and Music Appreciation Project, ensure a harmonious understanding of musical concepts with a high engagement level that fosters a lifelong appreciation for diverse melodies.",
      "topic": "Music",
      "age_range": "7-9",
      "learning_objectives": [
        "Musical Concepts",
        "Cultural Music Appreciation",
        "Instrument Exploration"
      ],
      "interactive_activities": [
        "DIY Musical Instruments",
        "Global Music Showcase"
      ],
      "recommended_resources": [
        "Children's Music Books",
        "Musical Instrument Kits"
      ],
      "assessment_methods": [
        "Melody Explorer Quiz",
        "Music Appreciation Project"
      ],
      "engagement_level": "High",
      "image": "https://example.com/music_explorers.jpg"
    },
    {
      "title": "Math Adventures: Exploring Numbers and Shapes",
      "author": "Professor Ellie",
      "id": 11,
      "content": "Embark on a magical journey of math exploration with Professor Ellie. Dive into the world of numbers, shapes, and patterns, making learning a delightful adventure for young minds. Join Professor Ellie on a magical journey of math exploration, inviting children aged 7 to 9 to dive into the world of numbers, shapes, and patterns. This blog makes learning a delightful adventure, exploring the wonders of mathematics and its real-world applications. Engage in math puzzles, play shape sorting games, and discover the joy of numbers. Recommended resources include mathematics workbooks for kids and educational math apps, providing a foundation for mathematical literacy. Assessment methods, such as fun quizzes and hands-on activities, ensure a comprehensive understanding of mathematical concepts with a high engagement level that transforms learning into a delightful adventure.",
      "topic": "Mathematics",
      "age_range": "7-9",
      "learning_objectives": [
        "Number Recognition",
        "Geometry",
        "Patterns"
      ],
      "interactive_activities": [
        "Math Puzzles",
        "Shape Sorting Games"
      ],
      "recommended_resources": [
        "Mathematics Workbook for Kids",
        "Educational Math Apps"
      ],
      "assessment_methods": [
        "Fun Quizzes",
        "Hands-on Activities"
      ],
      "engagement_level": "High",
      "image": "https://example.com/math_adventures.jpg"
    },
    {
      "id": 12,
      "title": "Story time with grandma",
      "body": "it all happened a long time ago in a faraway land called ushi",
      "author": "black pen"
    },
    {
      "id": 13,
      "title": "Story time with grandma",
      "body": "it all happened a long time ago in a faraway land called ushi",
      "author": "black pen"
    }
  ]
}